LICENSE
MANIFEST.in
README.md
it.unbit.uwsgi.emperor.plist
setup.py
bin/uwsgidns
uwsgidns/__init__.py
uwsgidns/checker.py
uwsgidns/constants.py
uwsgidns/listener.py
uwsgidns/logging.py
uwsgidns/main.py
uwsgidns/server.py
uwsgidns/utils.py
uwsgidns.egg-info/PKG-INFO
uwsgidns.egg-info/SOURCES.txt
uwsgidns.egg-info/dependency_links.txt
uwsgidns.egg-info/not-zip-safe
uwsgidns.egg-info/requires.txt
uwsgidns.egg-info/top_level.txt