Metadata-Version: 1.1
Name: uwsgidns
Version: 1.0.1
Summary: Dinamically route to localhost request for uWSGI locally subscribed domains.
Home-page: https://github.com/20tab/uwsgi-local-dns-resolver
Author: Adriano Di Luzio
Author-email: adrianodl@hotmail.it
License: MIT
Keywords: uwsgi,dns,uwsgidns,localhost
Platform: UNKNOWN
Classifier: Programming Language :: Python
Classifier: Programming Language :: Python :: 3
Classifier: Development Status :: 6 - Mature
Classifier: Environment :: Other Environment
Classifier: Intended Audience :: Developers
Classifier: Intended Audience :: End Users/Desktop
Classifier: Intended Audience :: Information Technology
Classifier: License :: OSI Approved :: MIT License
Classifier: Operating System :: POSIX
Classifier: Operating System :: Unix
Classifier: Topic :: System :: Operating System
Classifier: Topic :: Internet :: Name Service (DNS)
Classifier: Topic :: Utilities
